{
  "config": {
    "games_per_matchup": 1000,
    "seed": 42,
    "bid": 2,
    "setup": "human_openings_bid2_weighted",
    "ussr_temps": [
      0.5,
      1.0,
      1.5,
      2.0,
      3.0,
      5.0
    ],
    "us_temps": [
      0.5,
      1.0,
      1.5,
      2.0,
      3.0,
      5.0
    ],
    "parallel_workers": 8
  },
  "matrix": [
    {
      "games": 1000,
      "ussr_temperature": 0.5,
      "us_temperature": 0.5,
      "elapsed_sec": 98.1619,
      "games_per_sec": 10.1873,
      "ussr_wins": 687,
      "us_wins": 288,
      "draws": 25,
      "decisive": 975,
      "ussr_wr": 70.4615,
      "us_wr": 29.5385,
      "defcon1": 261,
      "turn_limit": 608,
      "scoring_card_held": 0,
      "vp_threshold": 116,
      "avg_turn": 9.154,
      "avg_final_vp": 2.521
    },
    {
      "games": 1000,
      "ussr_temperature": 0.5,
      "us_temperature": 1.0,
      "elapsed_sec": 99.3486,
      "games_per_sec": 10.0656,
      "ussr_wins": 667,
      "us_wins": 309,
      "draws": 24,
      "decisive": 976,
      "ussr_wr": 68.3402,
      "us_wr": 31.6598,
      "defcon1": 248,
      "turn_limit": 643,
      "scoring_card_held": 0,
      "vp_threshold": 91,
      "avg_turn": 9.154,
      "avg_final_vp": 2.138
    },
    {
      "games": 1000,
      "ussr_temperature": 0.5,
      "us_temperature": 1.5,
      "elapsed_sec": 99.3944,
      "games_per_sec": 10.0609,
      "ussr_wins": 661,
      "us_wins": 314,
      "draws": 25,
      "decisive": 975,
      "ussr_wr": 67.7949,
      "us_wr": 32.2051,
      "defcon1": 253,
      "turn_limit": 648,
      "scoring_card_held": 0,
      "vp_threshold": 83,
      "avg_turn": 9.18,
      "avg_final_vp": 1.554
    },
    {
      "games": 1000,
      "ussr_temperature": 0.5,
      "us_temperature": 2.0,
      "elapsed_sec": 99.3158,
      "games_per_sec": 10.0689,
      "ussr_wins": 636,
      "us_wins": 342,
      "draws": 22,
      "decisive": 978,
      "ussr_wr": 65.0307,
      "us_wr": 34.9693,
      "defcon1": 272,
      "turn_limit": 634,
      "scoring_card_held": 0,
      "vp_threshold": 85,
      "avg_turn": 9.088,
      "avg_final_vp": 0.866
    },
    {
      "games": 1000,
      "ussr_temperature": 0.5,
      "us_temperature": 3.0,
      "elapsed_sec": 98.5763,
      "games_per_sec": 10.1444,
      "ussr_wins": 664,
      "us_wins": 318,
      "draws": 18,
      "decisive": 982,
      "ussr_wr": 67.6171,
      "us_wr": 32.3829,
      "defcon1": 274,
      "turn_limit": 609,
      "scoring_card_held": 0,
      "vp_threshold": 98,
      "avg_turn": 9.109,
      "avg_final_vp": 1.27
    },
    {
      "games": 1000,
      "ussr_temperature": 0.5,
      "us_temperature": 5.0,
      "elapsed_sec": 100.956,
      "games_per_sec": 9.90535,
      "ussr_wins": 643,
      "us_wins": 332,
      "draws": 25,
      "decisive": 975,
      "ussr_wr": 65.9487,
      "us_wr": 34.0513,
      "defcon1": 259,
      "turn_limit": 639,
      "scoring_card_held": 0,
      "vp_threshold": 89,
      "avg_turn": 9.153,
      "avg_final_vp": 0.79
    },
    {
      "games": 1000,
      "ussr_temperature": 1.0,
      "us_temperature": 0.5,
      "elapsed_sec": 99.6041,
      "games_per_sec": 10.0398,
      "ussr_wins": 704,
      "us_wins": 276,
      "draws": 20,
      "decisive": 980,
      "ussr_wr": 71.8367,
      "us_wr": 28.1633,
      "defcon1": 258,
      "turn_limit": 622,
      "scoring_card_held": 0,
      "vp_threshold": 101,
      "avg_turn": 9.17,
      "avg_final_vp": 2.752
    },
    {
      "games": 1000,
      "ussr_temperature": 1.0,
      "us_temperature": 1.0,
      "elapsed_sec": 102.113,
      "games_per_sec": 9.79307,
      "ussr_wins": 651,
      "us_wins": 322,
      "draws": 27,
      "decisive": 973,
      "ussr_wr": 66.9065,
      "us_wr": 33.0935,
      "defcon1": 268,
      "turn_limit": 626,
      "scoring_card_held": 0,
      "vp_threshold": 93,
      "avg_turn": 9.2,
      "avg_final_vp": 1.622
    },
    {
      "games": 1000,
      "ussr_temperature": 1.0,
      "us_temperature": 1.5,
      "elapsed_sec": 101.391,
      "games_per_sec": 9.86278,
      "ussr_wins": 637,
      "us_wins": 345,
      "draws": 18,
      "decisive": 982,
      "ussr_wr": 64.8676,
      "us_wr": 35.1324,
      "defcon1": 261,
      "turn_limit": 641,
      "scoring_card_held": 0,
      "vp_threshold": 86,
      "avg_turn": 9.228,
      "avg_final_vp": 0.363
    },
    {
      "games": 1000,
      "ussr_temperature": 1.0,
      "us_temperature": 2.0,
      "elapsed_sec": 99.4202,
      "games_per_sec": 10.0583,
      "ussr_wins": 653,
      "us_wins": 325,
      "draws": 22,
      "decisive": 978,
      "ussr_wr": 66.7689,
      "us_wr": 33.2311,
      "defcon1": 276,
      "turn_limit": 609,
      "scoring_card_held": 0,
      "vp_threshold": 95,
      "avg_turn": 9.172,
      "avg_final_vp": 0.874
    },
    {
      "games": 1000,
      "ussr_temperature": 1.0,
      "us_temperature": 3.0,
      "elapsed_sec": 98.3131,
      "games_per_sec": 10.1716,
      "ussr_wins": 661,
      "us_wins": 323,
      "draws": 16,
      "decisive": 984,
      "ussr_wr": 67.1748,
      "us_wr": 32.8252,
      "defcon1": 289,
      "turn_limit": 597,
      "scoring_card_held": 0,
      "vp_threshold": 100,
      "avg_turn": 9.07,
      "avg_final_vp": 0.774
    },
    {
      "games": 1000,
      "ussr_temperature": 1.0,
      "us_temperature": 5.0,
      "elapsed_sec": 99.5568,
      "games_per_sec": 10.0445,
      "ussr_wins": 668,
      "us_wins": 314,
      "draws": 18,
      "decisive": 982,
      "ussr_wr": 68.0244,
      "us_wr": 31.9756,
      "defcon1": 297,
      "turn_limit": 604,
      "scoring_card_held": 0,
      "vp_threshold": 86,
      "avg_turn": 9.107,
      "avg_final_vp": 0.99
    },
    {
      "games": 1000,
      "ussr_temperature": 1.5,
      "us_temperature": 0.5,
      "elapsed_sec": 97.1269,
      "games_per_sec": 10.2958,
      "ussr_wins": 693,
      "us_wins": 280,
      "draws": 27,
      "decisive": 973,
      "ussr_wr": 71.223,
      "us_wr": 28.777,
      "defcon1": 265,
      "turn_limit": 608,
      "scoring_card_held": 0,
      "vp_threshold": 115,
      "avg_turn": 9.141,
      "avg_final_vp": 2.661
    },
    {
      "games": 1000,
      "ussr_temperature": 1.5,
      "us_temperature": 1.0,
      "elapsed_sec": 99.4547,
      "games_per_sec": 10.0548,
      "ussr_wins": 659,
      "us_wins": 314,
      "draws": 27,
      "decisive": 973,
      "ussr_wr": 67.7287,
      "us_wr": 32.2713,
      "defcon1": 267,
      "turn_limit": 604,
      "scoring_card_held": 0,
      "vp_threshold": 114,
      "avg_turn": 9.217,
      "avg_final_vp": 1.668
    },
    {
      "games": 1000,
      "ussr_temperature": 1.5,
      "us_temperature": 1.5,
      "elapsed_sec": 98.0855,
      "games_per_sec": 10.1952,
      "ussr_wins": 682,
      "us_wins": 293,
      "draws": 25,
      "decisive": 975,
      "ussr_wr": 69.9487,
      "us_wr": 30.0513,
      "defcon1": 284,
      "turn_limit": 593,
      "scoring_card_held": 0,
      "vp_threshold": 107,
      "avg_turn": 9.128,
      "avg_final_vp": 1.645
    },
    {
      "games": 1000,
      "ussr_temperature": 1.5,
      "us_temperature": 2.0,
      "elapsed_sec": 98.601,
      "games_per_sec": 10.1419,
      "ussr_wins": 625,
      "us_wins": 357,
      "draws": 18,
      "decisive": 982,
      "ussr_wr": 63.6456,
      "us_wr": 36.3544,
      "defcon1": 270,
      "turn_limit": 613,
      "scoring_card_held": 0,
      "vp_threshold": 106,
      "avg_turn": 9.1,
      "avg_final_vp": 0.241
    },
    {
      "games": 1000,
      "ussr_temperature": 1.5,
      "us_temperature": 3.0,
      "elapsed_sec": 105.705,
      "games_per_sec": 9.46025,
      "ussr_wins": 640,
      "us_wins": 334,
      "draws": 26,
      "decisive": 974,
      "ussr_wr": 65.7084,
      "us_wr": 34.2916,
      "defcon1": 287,
      "turn_limit": 596,
      "scoring_card_held": 0,
      "vp_threshold": 102,
      "avg_turn": 9.066,
      "avg_final_vp": 0.466
    },
    {
      "games": 1000,
      "ussr_temperature": 1.5,
      "us_temperature": 5.0,
      "elapsed_sec": 108.688,
      "games_per_sec": 9.20064,
      "ussr_wins": 657,
      "us_wins": 322,
      "draws": 21,
      "decisive": 979,
      "ussr_wr": 67.1093,
      "us_wr": 32.8907,
      "defcon1": 271,
      "turn_limit": 627,
      "scoring_card_held": 0,
      "vp_threshold": 92,
      "avg_turn": 9.162,
      "avg_final_vp": 0.832
    },
    {
      "games": 1000,
      "ussr_temperature": 2.0,
      "us_temperature": 0.5,
      "elapsed_sec": 106.512,
      "games_per_sec": 9.38866,
      "ussr_wins": 683,
      "us_wins": 302,
      "draws": 15,
      "decisive": 985,
      "ussr_wr": 69.3401,
      "us_wr": 30.6599,
      "defcon1": 267,
      "turn_limit": 610,
      "scoring_card_held": 0,
      "vp_threshold": 108,
      "avg_turn": 9.164,
      "avg_final_vp": 2.35
    },
    {
      "games": 1000,
      "ussr_temperature": 2.0,
      "us_temperature": 1.0,
      "elapsed_sec": 105.009,
      "games_per_sec": 9.52301,
      "ussr_wins": 679,
      "us_wins": 298,
      "draws": 23,
      "decisive": 977,
      "ussr_wr": 69.4985,
      "us_wr": 30.5015,
      "defcon1": 294,
      "turn_limit": 591,
      "scoring_card_held": 0,
      "vp_threshold": 104,
      "avg_turn": 9.059,
      "avg_final_vp": 1.605
    },
    {
      "games": 1000,
      "ussr_temperature": 2.0,
      "us_temperature": 1.5,
      "elapsed_sec": 107.277,
      "games_per_sec": 9.3217,
      "ussr_wins": 662,
      "us_wins": 323,
      "draws": 15,
      "decisive": 985,
      "ussr_wr": 67.2081,
      "us_wr": 32.7919,
      "defcon1": 270,
      "turn_limit": 606,
      "scoring_card_held": 0,
      "vp_threshold": 107,
      "avg_turn": 9.148,
      "avg_final_vp": 1.592
    },
    {
      "games": 1000,
      "ussr_temperature": 2.0,
      "us_temperature": 2.0,
      "elapsed_sec": 107.605,
      "games_per_sec": 9.29327,
      "ussr_wins": 628,
      "us_wins": 349,
      "draws": 23,
      "decisive": 977,
      "ussr_wr": 64.2784,
      "us_wr": 35.7216,
      "defcon1": 259,
      "turn_limit": 636,
      "scoring_card_held": 0,
      "vp_threshold": 93,
      "avg_turn": 9.118,
      "avg_final_vp": 0.429
    },
    {
      "games": 1000,
      "ussr_temperature": 2.0,
      "us_temperature": 3.0,
      "elapsed_sec": 107.454,
      "games_per_sec": 9.30627,
      "ussr_wins": 608,
      "us_wins": 372,
      "draws": 20,
      "decisive": 980,
      "ussr_wr": 62.0408,
      "us_wr": 37.9592,
      "defcon1": 272,
      "turn_limit": 608,
      "scoring_card_held": 0,
      "vp_threshold": 108,
      "avg_turn": 9.143,
      "avg_final_vp": -0.031
    },
    {
      "games": 1000,
      "ussr_temperature": 2.0,
      "us_temperature": 5.0,
      "elapsed_sec": 109.36,
      "games_per_sec": 9.14414,
      "ussr_wins": 672,
      "us_wins": 315,
      "draws": 13,
      "decisive": 987,
      "ussr_wr": 68.0851,
      "us_wr": 31.9149,
      "defcon1": 275,
      "turn_limit": 623,
      "scoring_card_held": 0,
      "vp_threshold": 91,
      "avg_turn": 9.209,
      "avg_final_vp": 1.629
    },
    {
      "games": 1000,
      "ussr_temperature": 3.0,
      "us_temperature": 0.5,
      "elapsed_sec": 107.449,
      "games_per_sec": 9.30676,
      "ussr_wins": 665,
      "us_wins": 311,
      "draws": 24,
      "decisive": 976,
      "ussr_wr": 68.1352,
      "us_wr": 31.8648,
      "defcon1": 280,
      "turn_limit": 601,
      "scoring_card_held": 0,
      "vp_threshold": 107,
      "avg_turn": 9.116,
      "avg_final_vp": 1.648
    },
    {
      "games": 1000,
      "ussr_temperature": 3.0,
      "us_temperature": 1.0,
      "elapsed_sec": 106.703,
      "games_per_sec": 9.37185,
      "ussr_wins": 664,
      "us_wins": 314,
      "draws": 22,
      "decisive": 978,
      "ussr_wr": 67.8937,
      "us_wr": 32.1063,
      "defcon1": 289,
      "turn_limit": 584,
      "scoring_card_held": 0,
      "vp_threshold": 110,
      "avg_turn": 9.067,
      "avg_final_vp": 1.192
    },
    {
      "games": 1000,
      "ussr_temperature": 3.0,
      "us_temperature": 1.5,
      "elapsed_sec": 108.109,
      "games_per_sec": 9.24993,
      "ussr_wins": 642,
      "us_wins": 338,
      "draws": 20,
      "decisive": 980,
      "ussr_wr": 65.5102,
      "us_wr": 34.4898,
      "defcon1": 272,
      "turn_limit": 619,
      "scoring_card_held": 0,
      "vp_threshold": 92,
      "avg_turn": 9.142,
      "avg_final_vp": 0.875
    },
    {
      "games": 1000,
      "ussr_temperature": 3.0,
      "us_temperature": 2.0,
      "elapsed_sec": 107.264,
      "games_per_sec": 9.32278,
      "ussr_wins": 651,
      "us_wins": 328,
      "draws": 21,
      "decisive": 979,
      "ussr_wr": 66.4964,
      "us_wr": 33.5036,
      "defcon1": 304,
      "turn_limit": 583,
      "scoring_card_held": 0,
      "vp_threshold": 94,
      "avg_turn": 9.065,
      "avg_final_vp": 0.319
    },
    {
      "games": 1000,
      "ussr_temperature": 3.0,
      "us_temperature": 3.0,
      "elapsed_sec": 108.463,
      "games_per_sec": 9.21969,
      "ussr_wins": 622,
      "us_wins": 357,
      "draws": 21,
      "decisive": 979,
      "ussr_wr": 63.5342,
      "us_wr": 36.4658,
      "defcon1": 289,
      "turn_limit": 589,
      "scoring_card_held": 0,
      "vp_threshold": 109,
      "avg_turn": 9.134,
      "avg_final_vp": 0.036
    },
    {
      "games": 1000,
      "ussr_temperature": 3.0,
      "us_temperature": 5.0,
      "elapsed_sec": 110.585,
      "games_per_sec": 9.0428,
      "ussr_wins": 638,
      "us_wins": 336,
      "draws": 26,
      "decisive": 974,
      "ussr_wr": 65.5031,
      "us_wr": 34.4969,
      "defcon1": 274,
      "turn_limit": 601,
      "scoring_card_held": 0,
      "vp_threshold": 117,
      "avg_turn": 9.164,
      "avg_final_vp": 0.984
    },
    {
      "games": 1000,
      "ussr_temperature": 5.0,
      "us_temperature": 0.5,
      "elapsed_sec": 107.255,
      "games_per_sec": 9.3236,
      "ussr_wins": 639,
      "us_wins": 345,
      "draws": 16,
      "decisive": 984,
      "ussr_wr": 64.939,
      "us_wr": 35.061,
      "defcon1": 278,
      "turn_limit": 587,
      "scoring_card_held": 0,
      "vp_threshold": 119,
      "avg_turn": 9.137,
      "avg_final_vp": 0.271
    },
    {
      "games": 1000,
      "ussr_temperature": 5.0,
      "us_temperature": 1.0,
      "elapsed_sec": 107.449,
      "games_per_sec": 9.30671,
      "ussr_wins": 634,
      "us_wins": 352,
      "draws": 14,
      "decisive": 986,
      "ussr_wr": 64.3002,
      "us_wr": 35.6998,
      "defcon1": 267,
      "turn_limit": 615,
      "scoring_card_held": 0,
      "vp_threshold": 104,
      "avg_turn": 9.143,
      "avg_final_vp": 0.439
    },
    {
      "games": 1000,
      "ussr_temperature": 5.0,
      "us_temperature": 1.5,
      "elapsed_sec": 104.681,
      "games_per_sec": 9.55282,
      "ussr_wins": 616,
      "us_wins": 359,
      "draws": 25,
      "decisive": 975,
      "ussr_wr": 63.1795,
      "us_wr": 36.8205,
      "defcon1": 271,
      "turn_limit": 619,
      "scoring_card_held": 0,
      "vp_threshold": 94,
      "avg_turn": 9.145,
      "avg_final_vp": -0.095
    },
    {
      "games": 1000,
      "ussr_temperature": 5.0,
      "us_temperature": 2.0,
      "elapsed_sec": 104.512,
      "games_per_sec": 9.56832,
      "ussr_wins": 607,
      "us_wins": 370,
      "draws": 23,
      "decisive": 977,
      "ussr_wr": 62.129,
      "us_wr": 37.871,
      "defcon1": 278,
      "turn_limit": 595,
      "scoring_card_held": 0,
      "vp_threshold": 106,
      "avg_turn": 9.115,
      "avg_final_vp": -0.579
    },
    {
      "games": 1000,
      "ussr_temperature": 5.0,
      "us_temperature": 3.0,
      "elapsed_sec": 104.051,
      "games_per_sec": 9.61068,
      "ussr_wins": 602,
      "us_wins": 375,
      "draws": 23,
      "decisive": 977,
      "ussr_wr": 61.6172,
      "us_wr": 38.3828,
      "defcon1": 299,
      "turn_limit": 589,
      "scoring_card_held": 0,
      "vp_threshold": 96,
      "avg_turn": 9.017,
      "avg_final_vp": -0.831
    },
    {
      "games": 1000,
      "ussr_temperature": 5.0,
      "us_temperature": 5.0,
      "elapsed_sec": 106.753,
      "games_per_sec": 9.36744,
      "ussr_wins": 632,
      "us_wins": 350,
      "draws": 18,
      "decisive": 982,
      "ussr_wr": 64.3585,
      "us_wr": 35.6415,
      "defcon1": 278,
      "turn_limit": 616,
      "scoring_card_held": 0,
      "vp_threshold": 97,
      "avg_turn": 9.111,
      "avg_final_vp": -0.219
    }
  ]
}
