{
  "anchor": "v14",
  "anchor_elo": 2015.0,
  "bipartite_anchor": "v14_USSR",
  "games_per_match": 200,
  "games_per_side": 100,
  "schedule": "round_robin",
  "ratings": {
    "v55": {
      "elo": 2118.8,
      "elo_ussr": 2087.9,
      "elo_us": 2033.9,
      "ci95": [
        2105.8,
        2131.8
      ],
      "delta_vs_anchor": 103.8
    },
    "v46": {
      "elo": 2103.7,
      "elo_ussr": 2083.7,
      "elo_us": 2006.3,
      "ci95": [
        2090.7,
        2116.6
      ],
      "delta_vs_anchor": 88.7
    },
    "v54": {
      "elo": 2097.9,
      "elo_ussr": 2081.0,
      "elo_us": 1998.7,
      "ci95": [
        2084.9,
        2110.8
      ],
      "delta_vs_anchor": 82.9
    },
    "v44": {
      "elo": 2091.2,
      "elo_ussr": 2055.9,
      "elo_us": 2007.2,
      "ci95": [
        2078.4,
        2104.1
      ],
      "delta_vs_anchor": 76.2
    },
    "v45": {
      "elo": 2082.8,
      "elo_ussr": 2102.2,
      "elo_us": 1947.7,
      "ci95": [
        2069.9,
        2095.7
      ],
      "delta_vs_anchor": 67.8
    },
    "v59": {
      "elo": 2032.6,
      "elo_ussr": 1999.1,
      "elo_us": 1942.7,
      "ci95": [
        2019.7,
        2045.5
      ],
      "delta_vs_anchor": 17.6
    },
    "v14": {
      "elo": 2015.0,
      "elo_ussr": 2015.0,
      "elo_us": 1884.9,
      "ci95": [
        2015.0,
        2015.0
      ],
      "delta_vs_anchor": 0.0
    },
    "v53": {
      "elo": 1991.3,
      "elo_ussr": 1952.9,
      "elo_us": 1902.7,
      "ci95": [
        1978.2,
        2004.4
      ],
      "delta_vs_anchor": -23.7
    },
    "v84_sc": {
      "elo": 1944.7,
      "elo_ussr": 1915.9,
      "elo_us": 1838.4,
      "ci95": [
        1926.3,
        1963.1
      ],
      "delta_vs_anchor": -70.3
    }
  },
  "matches": [
    {
      "model_a": "v55",
      "model_b": "v54",
      "n_games": 400,
      "seed": 97600,
      "wins_a": 209,
      "wins_b": 181,
      "draws": 10,
      "wins_a_ussr": 115,
      "wins_b_ussr": 102,
      "wins_a_us": 94,
      "wins_b_us": 79,
      "wr_a": 0.535,
      "reused": true
    },
    {
      "model_a": "v55",
      "model_b": "v44",
      "n_games": 400,
      "seed": 93600,
      "wins_a": 201,
      "wins_b": 178,
      "draws": 21,
      "wins_a_ussr": 119,
      "wins_b_ussr": 110,
      "wins_a_us": 82,
      "wins_b_us": 68,
      "wr_a": 0.5288,
      "reused": true
    },
    {
      "model_a": "v55",
      "model_b": "v45",
      "n_games": 400,
      "seed": 94000,
      "wins_a": 206,
      "wins_b": 180,
      "draws": 14,
      "wins_a_ussr": 136,
      "wins_b_ussr": 123,
      "wins_a_us": 70,
      "wins_b_us": 57,
      "wr_a": 0.5325,
      "reused": true
    },
    {
      "model_a": "v55",
      "model_b": "v14",
      "n_games": 400,
      "seed": 90000,
      "wins_a": 255,
      "wins_b": 128,
      "draws": 17,
      "wins_a_ussr": 150,
      "wins_b_ussr": 88,
      "wins_a_us": 105,
      "wins_b_us": 40,
      "wr_a": 0.6587,
      "reused": true
    },
    {
      "model_a": "v55",
      "model_b": "v53",
      "n_games": 400,
      "seed": 97200,
      "wins_a": 249,
      "wins_b": 137,
      "draws": 14,
      "wins_a_ussr": 133,
      "wins_b_ussr": 78,
      "wins_a_us": 116,
      "wins_b_us": 59,
      "wr_a": 0.64,
      "reused": true
    },
    {
      "model_a": "v55",
      "model_b": "v59",
      "n_games": 400,
      "seed": 98000,
      "wins_a": 240,
      "wins_b": 150,
      "draws": 10,
      "wins_a_ussr": 133,
      "wins_b_ussr": 91,
      "wins_a_us": 107,
      "wins_b_us": 59,
      "wr_a": 0.6125,
      "reused": true
    },
    {
      "model_a": "v55",
      "model_b": "v46",
      "n_games": 400,
      "seed": 94400,
      "wins_a": 201,
      "wins_b": 184,
      "draws": 15,
      "wins_a_ussr": 114,
      "wins_b_ussr": 107,
      "wins_a_us": 87,
      "wins_b_us": 77,
      "wr_a": 0.5212,
      "reused": true
    },
    {
      "model_a": "v55",
      "model_b": "v84_sc",
      "n_games": 200,
      "seed": 88000,
      "wins_a": 159,
      "wins_b": 39,
      "draws": 2,
      "wins_a_ussr": 88,
      "wins_b_ussr": 29,
      "wins_a_us": 71,
      "wins_b_us": 10,
      "wr_a": 0.8
    },
    {
      "model_a": "v54",
      "model_b": "v44",
      "n_games": 400,
      "seed": 92000,
      "wins_a": 222,
      "wins_b": 163,
      "draws": 15,
      "wins_a_ussr": 126,
      "wins_b_ussr": 99,
      "wins_a_us": 96,
      "wins_b_us": 64,
      "wr_a": 0.5737,
      "reused": true
    },
    {
      "model_a": "v54",
      "model_b": "v45",
      "n_games": 400,
      "seed": 92400,
      "wins_a": 194,
      "wins_b": 183,
      "draws": 23,
      "wins_a_ussr": 125,
      "wins_b_ussr": 121,
      "wins_a_us": 69,
      "wins_b_us": 62,
      "wr_a": 0.5138,
      "reused": true
    },
    {
      "model_a": "v54",
      "model_b": "v14",
      "n_games": 400,
      "seed": 88400,
      "wins_a": 254,
      "wins_b": 131,
      "draws": 15,
      "wins_a_ussr": 154,
      "wins_b_ussr": 95,
      "wins_a_us": 100,
      "wins_b_us": 36,
      "wr_a": 0.6538,
      "reused": true
    },
    {
      "model_a": "v54",
      "model_b": "v53",
      "n_games": 400,
      "seed": 95600,
      "wins_a": 241,
      "wins_b": 145,
      "draws": 14,
      "wins_a_ussr": 147,
      "wins_b_ussr": 102,
      "wins_a_us": 94,
      "wins_b_us": 43,
      "wr_a": 0.62,
      "reused": true
    },
    {
      "model_a": "v54",
      "model_b": "v59",
      "n_games": 400,
      "seed": 97600,
      "wins_a": 214,
      "wins_b": 167,
      "draws": 19,
      "wins_a_ussr": 123,
      "wins_b_ussr": 102,
      "wins_a_us": 91,
      "wins_b_us": 65,
      "wr_a": 0.5587,
      "reused": true
    },
    {
      "model_a": "v54",
      "model_b": "v46",
      "n_games": 400,
      "seed": 92800,
      "wins_a": 181,
      "wins_b": 200,
      "draws": 19,
      "wins_a_ussr": 113,
      "wins_b_ussr": 120,
      "wins_a_us": 68,
      "wins_b_us": 80,
      "wr_a": 0.4763,
      "reused": true
    },
    {
      "model_a": "v54",
      "model_b": "v84_sc",
      "n_games": 200,
      "seed": 88200,
      "wins_a": 131,
      "wins_b": 68,
      "draws": 1,
      "wins_a_ussr": 73,
      "wins_b_ussr": 42,
      "wins_a_us": 58,
      "wins_b_us": 26,
      "wr_a": 0.6575
    },
    {
      "model_a": "v44",
      "model_b": "v45",
      "n_games": 400,
      "seed": 93600,
      "wins_a": 194,
      "wins_b": 192,
      "draws": 14,
      "wins_a_ussr": 130,
      "wins_b_ussr": 130,
      "wins_a_us": 64,
      "wins_b_us": 62,
      "wr_a": 0.5025,
      "reused": true
    },
    {
      "model_a": "v44",
      "model_b": "v14",
      "n_games": 400,
      "seed": 90000,
      "wins_a": 239,
      "wins_b": 147,
      "draws": 14,
      "wins_a_ussr": 147,
      "wins_b_ussr": 100,
      "wins_a_us": 92,
      "wins_b_us": 47,
      "wr_a": 0.615,
      "reused": true
    },
    {
      "model_a": "v44",
      "model_b": "v53",
      "n_games": 400,
      "seed": 93600,
      "wins_a": 254,
      "wins_b": 134,
      "draws": 12,
      "wins_a_ussr": 139,
      "wins_b_ussr": 80,
      "wins_a_us": 115,
      "wins_b_us": 54,
      "wr_a": 0.65,
      "reused": true
    },
    {
      "model_a": "v44",
      "model_b": "v59",
      "n_games": 400,
      "seed": 93600,
      "wins_a": 240,
      "wins_b": 146,
      "draws": 14,
      "wins_a_ussr": 131,
      "wins_b_ussr": 83,
      "wins_a_us": 109,
      "wins_b_us": 63,
      "wr_a": 0.6175,
      "reused": true
    },
    {
      "model_a": "v44",
      "model_b": "v46",
      "n_games": 400,
      "seed": 93600,
      "wins_a": 190,
      "wins_b": 190,
      "draws": 20,
      "wins_a_ussr": 102,
      "wins_b_ussr": 101,
      "wins_a_us": 88,
      "wins_b_us": 89,
      "wr_a": 0.5,
      "reused": true
    },
    {
      "model_a": "v44",
      "model_b": "v84_sc",
      "n_games": 200,
      "seed": 88400,
      "wins_a": 133,
      "wins_b": 65,
      "draws": 2,
      "wins_a_ussr": 73,
      "wins_b_ussr": 40,
      "wins_a_us": 60,
      "wins_b_us": 25,
      "wr_a": 0.67
    },
    {
      "model_a": "v45",
      "model_b": "v14",
      "n_games": 400,
      "seed": 90000,
      "wins_a": 226,
      "wins_b": 162,
      "draws": 12,
      "wins_a_ussr": 147,
      "wins_b_ussr": 115,
      "wins_a_us": 79,
      "wins_b_us": 47,
      "wr_a": 0.58,
      "reused": true
    },
    {
      "model_a": "v45",
      "model_b": "v53",
      "n_games": 400,
      "seed": 94000,
      "wins_a": 240,
      "wins_b": 143,
      "draws": 17,
      "wins_a_ussr": 141,
      "wins_b_ussr": 93,
      "wins_a_us": 99,
      "wins_b_us": 50,
      "wr_a": 0.6212,
      "reused": true
    },
    {
      "model_a": "v45",
      "model_b": "v59",
      "n_games": 400,
      "seed": 94000,
      "wins_a": 202,
      "wins_b": 179,
      "draws": 19,
      "wins_a_ussr": 126,
      "wins_b_ussr": 113,
      "wins_a_us": 76,
      "wins_b_us": 66,
      "wr_a": 0.5288,
      "reused": true
    },
    {
      "model_a": "v45",
      "model_b": "v46",
      "n_games": 400,
      "seed": 94000,
      "wins_a": 189,
      "wins_b": 194,
      "draws": 17,
      "wins_a_ussr": 130,
      "wins_b_ussr": 137,
      "wins_a_us": 59,
      "wins_b_us": 57,
      "wr_a": 0.4938,
      "reused": true
    },
    {
      "model_a": "v45",
      "model_b": "v84_sc",
      "n_games": 200,
      "seed": 88600,
      "wins_a": 134,
      "wins_b": 61,
      "draws": 5,
      "wins_a_ussr": 73,
      "wins_b_ussr": 38,
      "wins_a_us": 61,
      "wins_b_us": 23,
      "wr_a": 0.6825
    },
    {
      "model_a": "v14",
      "model_b": "v53",
      "n_games": 400,
      "seed": 90000,
      "wins_a": 222,
      "wins_b": 164,
      "draws": 14,
      "wins_a_ussr": 130,
      "wins_b_ussr": 101,
      "wins_a_us": 92,
      "wins_b_us": 63,
      "wr_a": 0.5725,
      "reused": true
    },
    {
      "model_a": "v14",
      "model_b": "v59",
      "n_games": 400,
      "seed": 90000,
      "wins_a": 182,
      "wins_b": 203,
      "draws": 15,
      "wins_a_ussr": 117,
      "wins_b_ussr": 128,
      "wins_a_us": 65,
      "wins_b_us": 75,
      "wr_a": 0.4738,
      "reused": true
    },
    {
      "model_a": "v14",
      "model_b": "v46",
      "n_games": 400,
      "seed": 90000,
      "wins_a": 139,
      "wins_b": 246,
      "draws": 15,
      "wins_a_ussr": 97,
      "wins_b_ussr": 151,
      "wins_a_us": 42,
      "wins_b_us": 95,
      "wr_a": 0.3663,
      "reused": true
    },
    {
      "model_a": "v14",
      "model_b": "v84_sc",
      "n_games": 200,
      "seed": 88800,
      "wins_a": 130,
      "wins_b": 64,
      "draws": 6,
      "wins_a_ussr": 77,
      "wins_b_ussr": 44,
      "wins_a_us": 53,
      "wins_b_us": 20,
      "wr_a": 0.665
    },
    {
      "model_a": "v53",
      "model_b": "v59",
      "n_games": 400,
      "seed": 97200,
      "wins_a": 181,
      "wins_b": 199,
      "draws": 20,
      "wins_a_ussr": 104,
      "wins_b_ussr": 113,
      "wins_a_us": 77,
      "wins_b_us": 86,
      "wr_a": 0.4775,
      "reused": true
    },
    {
      "model_a": "v53",
      "model_b": "v46",
      "n_games": 400,
      "seed": 94400,
      "wins_a": 137,
      "wins_b": 246,
      "draws": 17,
      "wins_a_ussr": 87,
      "wins_b_ussr": 141,
      "wins_a_us": 50,
      "wins_b_us": 105,
      "wr_a": 0.3638,
      "reused": true
    },
    {
      "model_a": "v53",
      "model_b": "v84_sc",
      "n_games": 200,
      "seed": 89000,
      "wins_a": 89,
      "wins_b": 102,
      "draws": 9,
      "wins_a_ussr": 51,
      "wins_b_ussr": 59,
      "wins_a_us": 38,
      "wins_b_us": 43,
      "wr_a": 0.4675
    },
    {
      "model_a": "v59",
      "model_b": "v46",
      "n_games": 400,
      "seed": 94400,
      "wins_a": 150,
      "wins_b": 230,
      "draws": 20,
      "wins_a_ussr": 91,
      "wins_b_ussr": 136,
      "wins_a_us": 59,
      "wins_b_us": 94,
      "wr_a": 0.4,
      "reused": true
    },
    {
      "model_a": "v59",
      "model_b": "v84_sc",
      "n_games": 200,
      "seed": 89200,
      "wins_a": 120,
      "wins_b": 74,
      "draws": 6,
      "wins_a_ussr": 74,
      "wins_b_ussr": 52,
      "wins_a_us": 46,
      "wins_b_us": 22,
      "wr_a": 0.615
    },
    {
      "model_a": "v46",
      "model_b": "v84_sc",
      "n_games": 200,
      "seed": 89400,
      "wins_a": 145,
      "wins_b": 47,
      "draws": 8,
      "wins_a_ussr": 82,
      "wins_b_ussr": 35,
      "wins_a_us": 63,
      "wins_b_us": 12,
      "wr_a": 0.745
    }
  ]
}